pygments_arm/__init__.py
pygments_arm-0.7.5.dist-info/LICENSE
pygments_arm-0.7.5.dist-info/METADATA
pygments_arm-0.7.5.dist-info/WHEEL
pygments_arm-0.7.5.dist-info/entry_points.txt
pygments_arm-0.7.5.dist-info/top_level.txt
pygments_arm-0.7.5.dist-info/RECORD
