Metadata-Version: 2.1
Name: pygments-arm
Version: 0.7.5
Summary: Pygments lexer for ARM.
Home-page: https://github.com/heia-fr/pygments-arm
Author: Jacques Supcik
Author-email: jacques.supcik@hefr.ch
License: Apache 2
Keywords: pygments arm assembler lexer
Platform: UNKNOWN
Classifier: Development Status :: 3 - Alpha
Classifier: Environment :: Plugins
Classifier: Intended Audience :: Developers
Classifier: License :: OSI Approved :: Apache Software License
Classifier: Operating System :: OS Independent
Classifier: Programming Language :: Python
Classifier: Programming Language :: Python :: 2
Classifier: Programming Language :: Python :: 3
Classifier: Topic :: Software Development :: Libraries :: Python Modules
Requires-Dist: pygments (>=1.4)
